[
  {
    "name": "Pretty Lethal",
    "type": "movie",
    "imdb_id": "tt26678938"
  },
  {
    "name": "Shelter",
    "type": "movie",
    "imdb_id": "tt32357218"
  },
  {
    "name": "War Machine",
    "type": "movie",
    "imdb_id": "tt15940132"
  },
  {
    "name": "Demon Slayer: Kimetsu no Yaiba Infinity Castle",
    "type": "movie",
    "imdb_id": "tt32820897"
  },
  {
    "name": "Mercy",
    "type": "movie",
    "imdb_id": "tt31050594"
  },
  {
    "name": "Dhurandhar: The Revenge",
    "type": "movie",
    "imdb_id": "tt39139925"
  },
  {
    "name": "The Wrecking Crew",
    "type": "movie",
    "imdb_id": "tt33046197"
  },
  {
    "name": "Hellfire",
    "type": "movie",
    "imdb_id": "tt14507394"
  },
  {
    "name": "Spider-Man: No Way Home",
    "type": "movie",
    "imdb_id": "tt10872600"
  },
  {
    "name": "The Legendary Lighter",
    "type": "movie",
    "imdb_id": "tt34510565"
  },
  {
    "name": "The Shadow's Edge",
    "type": "movie",
    "imdb_id": "tt34610311"
  },
  {
    "name": "Predator: Badlands",
    "type": "movie",
    "imdb_id": "tt31227572"
  },
  {
    "name": "The Avengers",
    "type": "movie",
    "imdb_id": "tt0848228"
  },
  {
    "name": "Ready or Not: Here I Come",
    "type": "movie",
    "imdb_id": "tt33978029"
  },
  {
    "name": "Hunting Season",
    "type": "movie",
    "imdb_id": "tt32537226"
  },
  {
    "name": "Dhurandhar",
    "type": "movie",
    "imdb_id": "tt33014583"
  },
  {
    "name": "They Will Kill You",
    "type": "movie",
    "imdb_id": "tt31728330"
  },
  {
    "name": "JUJUTSU KAISEN: Execution",
    "type": "movie",
    "imdb_id": "tt38121182"
  },
  {
    "name": "Sinners",
    "type": "movie",
    "imdb_id": "tt31193180"
  }
]