[
  {
    "name": "Playdate",
    "type": "movie",
    "imdb_id": "tt31425731"
  },
  {
    "name": "Code 3",
    "type": "movie",
    "imdb_id": "tt26394837"
  },
  {
    "name": "In Your Dreams",
    "type": "movie",
    "imdb_id": "tt27604215"
  },
  {
    "name": "Roofman",
    "type": "movie",
    "imdb_id": "tt4627382"
  },
  {
    "name": "Zootopia 2",
    "type": "movie",
    "imdb_id": "tt26443597"
  },
  {
    "name": "A Very Jonas Christmas Movie",
    "type": "movie",
    "imdb_id": "tt35600079"
  },
  {
    "name": "KPop Demon Hunters",
    "type": "movie",
    "imdb_id": "tt14205554"
  },
  {
    "name": "Grand Prix of Europe",
    "type": "movie",
    "imdb_id": "tt32897929"
  },
  {
    "name": "Afterburn",
    "type": "movie",
    "imdb_id": "tt1210027"
  },
  {
    "name": "Ko Ga Loak Village",
    "type": "movie",
    "imdb_id": "tt35020020"
  },
  {
    "name": "A Merry Little Ex-Mas",
    "type": "movie",
    "imdb_id": "tt34992378"
  },
  {
    "name": "The Toxic Avenger Unrated",
    "type": "movie",
    "imdb_id": "tt1633359"
  },
  {
    "name": "Colonel Kwiatkowski",
    "type": "movie",
    "imdb_id": "tt0114204"
  },
  {
    "name": "Stitch Head",
    "type": "movie",
    "imdb_id": "tt26720001"
  },
  {
    "name": "The Ugly Stepsister",
    "type": "movie",
    "imdb_id": "tt29344903"
  },
  {
    "name": "Fuuto PI: The Portrait of Kamen Rider Skull",
    "type": "movie",
    "imdb_id": "tt32809227"
  },
  {
    "name": "Laila",
    "type": "movie",
    "imdb_id": "tt32831759"
  },
  {
    "name": "Zootopia",
    "type": "movie",
    "imdb_id": "tt2948356"
  },
  {
    "name": "The Bad Guys 2",
    "type": "movie",
    "imdb_id": "tt30017619"
  },
  {
    "name": "Good Fortune",
    "type": "movie",
    "imdb_id": "tt27543578"
  }
]