[
  {
    "name": "The Manipulated",
    "type": "series",
    "imdb_id": "tt36188448"
  },
  {
    "name": "Daughter of Fire",
    "type": "series",
    "imdb_id": "tt32126001"
  },
  {
    "name": "Dancing with the Stars",
    "type": "series",
    "imdb_id": "tt0463398"
  },
  {
    "name": "Star Wars: The Clone Wars",
    "type": "series",
    "imdb_id": "tt0458290"
  },
  {
    "name": "The Mandalorian",
    "type": "series",
    "imdb_id": "tt8111088"
  },
  {
    "name": "Fortnite x The Simpsons",
    "type": "series",
    "imdb_id": "tt38821667"
  },
  {
    "name": "Disney Twisted-Wonderland: The Animation",
    "type": "series",
    "imdb_id": "tt28306749"
  },
  {
    "name": "Andor",
    "type": "series",
    "imdb_id": "tt9253284"
  },
  {
    "name": "Loki",
    "type": "series",
    "imdb_id": "tt9140554"
  },
  {
    "name": "Zootopia+",
    "type": "series",
    "imdb_id": "tt13622956"
  },
  {
    "name": "What If...?",
    "type": "series",
    "imdb_id": "tt10168312"
  },
  {
    "name": "Marvel Zombies",
    "type": "series",
    "imdb_id": "tt16027014"
  },
  {
    "name": "The Beatles Anthology",
    "type": "series",
    "imdb_id": "tt0111893"
  },
  {
    "name": "Daredevil: Born Again",
    "type": "series",
    "imdb_id": "tt18923754"
  },
  {
    "name": "Soy Luna",
    "type": "series",
    "imdb_id": "tt5189554"
  },
  {
    "name": "Star Wars: Visions",
    "type": "series",
    "imdb_id": "tt13622982"
  },
  {
    "name": "Moving",
    "type": "series",
    "imdb_id": "tt24640580"
  },
  {
    "name": "WandaVision",
    "type": "series",
    "imdb_id": "tt9140560"
  },
  {
    "name": "Hawkeye",
    "type": "series",
    "imdb_id": "tt10160804"
  },
  {
    "name": "Ironheart",
    "type": "series",
    "imdb_id": "tt13623126"
  }
]