[
  {
    "name": "Breakdown",
    "type": "series",
    "imdb_id": "tt35310911"
  },
  {
    "name": "Star Wars: The Clone Wars",
    "type": "series",
    "imdb_id": "tt0458290"
  },
  {
    "name": "The Mandalorian",
    "type": "series",
    "imdb_id": "tt8111088"
  },
  {
    "name": "Andor",
    "type": "series",
    "imdb_id": "tt9253284"
  },
  {
    "name": "Loki",
    "type": "series",
    "imdb_id": "tt9140554"
  },
  {
    "name": "Ironheart",
    "type": "series",
    "imdb_id": "tt13623126"
  },
  {
    "name": "Eyes of Wakanda",
    "type": "series",
    "imdb_id": "tt13968252"
  },
  {
    "name": "What If...?",
    "type": "series",
    "imdb_id": "tt10168312"
  },
  {
    "name": "Percy Jackson and the Olympians",
    "type": "series",
    "imdb_id": "tt12324366"
  },
  {
    "name": "Daredevil: Born Again",
    "type": "series",
    "imdb_id": "tt18923754"
  },
  {
    "name": "Soy Luna",
    "type": "series",
    "imdb_id": "tt5189554"
  },
  {
    "name": "Reminder",
    "type": "series",
    "imdb_id": "tt34995624"
  },
  {
    "name": "WandaVision",
    "type": "series",
    "imdb_id": "tt9140560"
  },
  {
    "name": "Takopi's Original Sin",
    "type": "series",
    "imdb_id": "tt36988358"
  },
  {
    "name": "Hawkeye",
    "type": "series",
    "imdb_id": "tt10160804"
  },
  {
    "name": "Moon Knight",
    "type": "series",
    "imdb_id": "tt10234724"
  },
  {
    "name": "I Am Groot",
    "type": "series",
    "imdb_id": "tt13623148"
  },
  {
    "name": "A Shop for Killers",
    "type": "series",
    "imdb_id": "tt26450613"
  },
  {
    "name": "The Falcon and the Winter Soldier",
    "type": "series",
    "imdb_id": "tt9208876"
  },
  {
    "name": "Dream Productions",
    "type": "series",
    "imdb_id": "tt33088401"
  }
]