[
  {
    "name": "The Simpsons",
    "type": "series",
    "imdb_id": "tt0096697"
  },
  {
    "name": "Gullak",
    "type": "series",
    "imdb_id": "tt10530900"
  },
  {
    "name": "Young Sheldon",
    "type": "series",
    "imdb_id": "tt6226232"
  },
  {
    "name": "Gaatchora",
    "type": "series",
    "imdb_id": "tt21907668"
  },
  {
    "name": "Deweni Inima",
    "type": "series",
    "imdb_id": "tt8943942"
  },
  {
    "name": "Elif",
    "type": "series",
    "imdb_id": "tt4745726"
  },
  {
    "name": "Frasier",
    "type": "series",
    "imdb_id": "tt0106004"
  },
  {
    "name": "Doraemon",
    "type": "series",
    "imdb_id": "tt4083422"
  },
  {
    "name": "Everwood",
    "type": "series",
    "imdb_id": "tt0318883"
  },
  {
    "name": "Teen Titans Go!",
    "type": "series",
    "imdb_id": "tt2771780"
  },
  {
    "name": "Pokémon Horizons",
    "type": "series",
    "imdb_id": "tt26692417"
  },
  {
    "name": "Gravity Falls",
    "type": "series",
    "imdb_id": "tt1865718"
  },
  {
    "name": "Bonanza",
    "type": "series",
    "imdb_id": "tt0052451"
  },
  {
    "name": "King of the Hill",
    "type": "series",
    "imdb_id": "tt0118375"
  },
  {
    "name": "Dallas",
    "type": "series",
    "imdb_id": "tt0077000"
  },
  {
    "name": "Dancing with the Stars",
    "type": "series",
    "imdb_id": "tt0463398"
  },
  {
    "name": "Phineas and Ferb",
    "type": "series",
    "imdb_id": "tt0852863"
  },
  {
    "name": "Yalı Çapkını",
    "type": "series",
    "imdb_id": "tt21105088"
  },
  {
    "name": "Diagnosis: Murder",
    "type": "series",
    "imdb_id": "tt0105986"
  },
  {
    "name": "The Promise",
    "type": "series",
    "imdb_id": "tt9826628"
  }
]