[
  {
    "name": "Among Friends",
    "type": "series",
    "imdb_id": "tt0175383"
  },
  {
    "name": "Jake and the Never Land Pirates",
    "type": "series",
    "imdb_id": "tt1833403"
  },
  {
    "name": "Doraemon",
    "type": "series",
    "imdb_id": "tt4083422"
  },
  {
    "name": "The Simpsons",
    "type": "series",
    "imdb_id": "tt0096697"
  },
  {
    "name": "The Tom and Jerry Show",
    "type": "series",
    "imdb_id": "tt3559124"
  },
  {
    "name": "Jeopardy!",
    "type": "series",
    "imdb_id": "tt0159881"
  },
  {
    "name": "Ninja Boy Rantaro",
    "type": "series",
    "imdb_id": "tt0306365"
  },
  {
    "name": "Ninja Hattori-kun",
    "type": "series",
    "imdb_id": "tt2787558"
  },
  {
    "name": "Teen Titans Go!",
    "type": "series",
    "imdb_id": "tt2771780"
  },
  {
    "name": "Scènes de ménages",
    "type": "series",
    "imdb_id": "tt1533783"
  },
  {
    "name": "The Smurfs",
    "type": "series",
    "imdb_id": "tt0081933"
  },
  {
    "name": "Doc McStuffins",
    "type": "series",
    "imdb_id": "tt1710295"
  },
  {
    "name": "The Wiggles",
    "type": "series",
    "imdb_id": "tt0454656"
  },
  {
    "name": "Sa Dulo Ng Walang Hanggan",
    "type": "series",
    "imdb_id": "tt0344713"
  },
  {
    "name": "Sazae-san",
    "type": "series",
    "imdb_id": "tt0236924"
  },
  {
    "name": "Ishqbaaaz",
    "type": "series",
    "imdb_id": "tt5919914"
  },
  {
    "name": "Diagnosis: Murder",
    "type": "series",
    "imdb_id": "tt0105986"
  },
  {
    "name": "Jodha & Akbar",
    "type": "series",
    "imdb_id": "tt3426342"
  },
  {
    "name": "Coucou c'est nous !",
    "type": "series",
    "imdb_id": "tt0366002"
  },
  {
    "name": "TV Animal Farm",
    "type": "series",
    "imdb_id": "tt25605188"
  }
]