[
  {
    "name": "Osiris",
    "type": "movie",
    "imdb_id": "tt31179712"
  },
  {
    "name": "Weapons",
    "type": "movie",
    "imdb_id": "tt26581740"
  },
  {
    "name": "Night Carnage",
    "type": "movie",
    "imdb_id": "tt12410182"
  },
  {
    "name": "Rob1n",
    "type": "movie",
    "imdb_id": "tt34493926"
  },
  {
    "name": "Shadow of God",
    "type": "movie",
    "imdb_id": "tt30442140"
  },
  {
    "name": "Popeye's Revenge",
    "type": "movie",
    "imdb_id": "tt33362807"
  },
  {
    "name": "Shaman",
    "type": "movie",
    "imdb_id": "tt28554021"
  },
  {
    "name": "28 Years Later",
    "type": "movie",
    "imdb_id": "tt10548174"
  },
  {
    "name": "Final Destination Bloodlines",
    "type": "movie",
    "imdb_id": "tt9619824"
  },
  {
    "name": "Bring Her Back",
    "type": "movie",
    "imdb_id": "tt32246771"
  },
  {
    "name": "Screamboat",
    "type": "movie",
    "imdb_id": "tt30766582"
  },
  {
    "name": "Site",
    "type": "movie",
    "imdb_id": "tt10278542"
  },
  {
    "name": "Hallow Road",
    "type": "movie",
    "imdb_id": "tt19403516"
  },
  {
    "name": "The Ritual",
    "type": "movie",
    "imdb_id": "tt32194932"
  },
  {
    "name": "Abraham's Boys",
    "type": "movie",
    "imdb_id": "tt14808764"
  },
  {
    "name": "Dangerous Animals",
    "type": "movie",
    "imdb_id": "tt32299316"
  },
  {
    "name": "Angels Fallen: Warriors of Peace",
    "type": "movie",
    "imdb_id": "tt20258220"
  },
  {
    "name": "Hook",
    "type": "movie",
    "imdb_id": "tt32635940"
  },
  {
    "name": "Together",
    "type": "movie",
    "imdb_id": "tt31184028"
  },
  {
    "name": "Sinners",
    "type": "movie",
    "imdb_id": "tt31193180"
  }
]