[
  {
    "name": "Pretty Lethal",
    "type": "movie",
    "imdb_id": "tt26678938"
  },
  {
    "name": "Send Help",
    "type": "movie",
    "imdb_id": "tt8036976"
  },
  {
    "name": "Scream 7",
    "type": "movie",
    "imdb_id": "tt27047903"
  },
  {
    "name": "Lake Jesup: Bonecrusher's Revenge",
    "type": "movie",
    "imdb_id": "tt30782197"
  },
  {
    "name": "Whistle",
    "type": "movie",
    "imdb_id": "tt29550683"
  },
  {
    "name": "Do Not Enter",
    "type": "movie",
    "imdb_id": "tt3515878"
  },
  {
    "name": "Return to Silent Hill",
    "type": "movie",
    "imdb_id": "tt22868010"
  },
  {
    "name": "The Deadly Little Mermaid",
    "type": "movie",
    "imdb_id": "tt37455571"
  },
  {
    "name": "Play Dead",
    "type": "movie",
    "imdb_id": "tt34793095"
  },
  {
    "name": "Anaconda",
    "type": "movie",
    "imdb_id": "tt33244668"
  },
  {
    "name": "The Draft!",
    "type": "movie",
    "imdb_id": "tt29941083"
  },
  {
    "name": "Ready or Not: Here I Come",
    "type": "movie",
    "imdb_id": "tt33978029"
  },
  {
    "name": "Sinners",
    "type": "movie",
    "imdb_id": "tt31193180"
  },
  {
    "name": "Frenzy",
    "type": "movie",
    "imdb_id": "tt0068611"
  },
  {
    "name": "They Will Kill You",
    "type": "movie",
    "imdb_id": "tt31728330"
  },
  {
    "name": "28 Years Later: The Bone Temple",
    "type": "movie",
    "imdb_id": "tt32141377"
  },
  {
    "name": "Dinosaurus!",
    "type": "movie",
    "imdb_id": "tt0053768"
  },
  {
    "name": "Lilly Lives Alone",
    "type": "movie",
    "imdb_id": "tt22169494"
  },
  {
    "name": "Terrestrial",
    "type": "movie",
    "imdb_id": "tt25967234"
  },
  {
    "name": "The Unearthly",
    "type": "movie",
    "imdb_id": "tt0051134"
  }
]