[
  {
    "name": "Scream 7",
    "type": "movie",
    "imdb_id": "tt27047903"
  },
  {
    "name": "Send Help",
    "type": "movie",
    "imdb_id": "tt8036976"
  },
  {
    "name": "Whistle",
    "type": "movie",
    "imdb_id": "tt29550683"
  },
  {
    "name": "Lake Jesup: Bonecrusher's Revenge",
    "type": "movie",
    "imdb_id": "tt30782197"
  },
  {
    "name": "Return to Silent Hill",
    "type": "movie",
    "imdb_id": "tt22868010"
  },
  {
    "name": "Play Dead",
    "type": "movie",
    "imdb_id": "tt34793095"
  },
  {
    "name": "Bloodline Killer",
    "type": "movie",
    "imdb_id": "tt13899250"
  },
  {
    "name": "Anaconda",
    "type": "movie",
    "imdb_id": "tt33244668"
  },
  {
    "name": "Lilly Lives Alone",
    "type": "movie",
    "imdb_id": "tt22169494"
  },
  {
    "name": "Sinners",
    "type": "movie",
    "imdb_id": "tt31193180"
  },
  {
    "name": "The Deadly Little Mermaid",
    "type": "movie",
    "imdb_id": "tt37455571"
  },
  {
    "name": "The Unearthly",
    "type": "movie",
    "imdb_id": "tt0051134"
  },
  {
    "name": "Stung",
    "type": "movie",
    "imdb_id": "tt3300572"
  },
  {
    "name": "28 Years Later: The Bone Temple",
    "type": "movie",
    "imdb_id": "tt32141377"
  },
  {
    "name": "Ready or Not: Here I Come",
    "type": "movie",
    "imdb_id": "tt33978029"
  },
  {
    "name": "Cold Storage",
    "type": "movie",
    "imdb_id": "tt8879928"
  },
  {
    "name": "Kraken",
    "type": "movie",
    "imdb_id": "tt19838566"
  },
  {
    "name": "Dracula",
    "type": "movie",
    "imdb_id": "tt31434030"
  },
  {
    "name": "Re/Member: The Last Night",
    "type": "movie",
    "imdb_id": "tt38219225"
  },
  {
    "name": "Osiris",
    "type": "movie",
    "imdb_id": "tt31179712"
  }
]