[
  {
    "name": "Néro the Assassin",
    "type": "series",
    "imdb_id": "tt32400599"
  },
  {
    "name": "Alice in Borderland",
    "type": "series",
    "imdb_id": "tt10795658"
  },
  {
    "name": "Wednesday",
    "type": "series",
    "imdb_id": "tt13443470"
  },
  {
    "name": "Stranger Things",
    "type": "series",
    "imdb_id": "tt4574334"
  },
  {
    "name": "Old Money",
    "type": "series",
    "imdb_id": "tt34692051"
  },
  {
    "name": "Boots",
    "type": "series",
    "imdb_id": "tt27987047"
  },
  {
    "name": "Genie, Make a Wish",
    "type": "series",
    "imdb_id": "tt32409807"
  },
  {
    "name": "Raw",
    "type": "series",
    "imdb_id": "tt0185103"
  },
  {
    "name": "Sex Education",
    "type": "series",
    "imdb_id": "tt7767422"
  },
  {
    "name": "Lucifer",
    "type": "series",
    "imdb_id": "tt4052886"
  },
  {
    "name": "Squid Game",
    "type": "series",
    "imdb_id": "tt10919420"
  },
  {
    "name": "You",
    "type": "series",
    "imdb_id": "tt7335184"
  },
  {
    "name": "Splinter Cell: Deathwatch",
    "type": "series",
    "imdb_id": "tt12809802"
  },
  {
    "name": "Outer Banks",
    "type": "series",
    "imdb_id": "tt10293938"
  },
  {
    "name": "True Haunting",
    "type": "series",
    "imdb_id": "tt38362312"
  },
  {
    "name": "The Diplomat",
    "type": "series",
    "imdb_id": "tt17491088"
  },
  {
    "name": "The Witcher",
    "type": "series",
    "imdb_id": "tt5180504"
  },
  {
    "name": "Weak Hero",
    "type": "series",
    "imdb_id": "tt20234568"
  },
  {
    "name": "The Guest",
    "type": "series",
    "imdb_id": "tt37065878"
  }
]