[
  {
    "name": "SPY x FAMILY",
    "type": "series",
    "imdb_id": "tt13706018"
  },
  {
    "name": "Detective Conan",
    "type": "series",
    "imdb_id": "tt0131179"
  },
  {
    "name": "Shine on Me",
    "type": "series",
    "imdb_id": "tt34852924"
  },
  {
    "name": "Men on a Mission",
    "type": "series",
    "imdb_id": "tt5247622"
  },
  {
    "name": "Taxi Driver",
    "type": "series",
    "imdb_id": "tt13759970"
  },
  {
    "name": "A Record of a Mortal's Journey to Immortality",
    "type": "series",
    "imdb_id": "tt12879782"
  },
  {
    "name": "Fights Break Sphere",
    "type": "series",
    "imdb_id": "tt12409194"
  },
  {
    "name": "Natural High",
    "type": "series",
    "imdb_id": "tt30461072"
  },
  {
    "name": "Me and Thee",
    "type": "series",
    "imdb_id": "tt34929687"
  },
  {
    "name": "Hello Saturday",
    "type": "series",
    "imdb_id": "tt30985733"
  },
  {
    "name": "Match of the Day",
    "type": "series",
    "imdb_id": "tt0135733"
  },
  {
    "name": "TMZ",
    "type": "series",
    "imdb_id": "tt1095213"
  },
  {
    "name": "Murders in...",
    "type": "series",
    "imdb_id": "tt4571004"
  },
  {
    "name": "Uncle",
    "type": "series",
    "imdb_id": "tt34607647"
  },
  {
    "name": "May I Ask for One Final Thing?",
    "type": "series",
    "imdb_id": "tt33384856"
  },
  {
    "name": "Surely Tomorrow",
    "type": "series",
    "imdb_id": "tt38221085"
  },
  {
    "name": "Três Graças",
    "type": "series",
    "imdb_id": "tt38591370"
  },
  {
    "name": "To Your Eternity",
    "type": "series",
    "imdb_id": "tt12063450"
  },
  {
    "name": "The Manager",
    "type": "series",
    "imdb_id": "tt15340934"
  },
  {
    "name": "To My Shore",
    "type": "series",
    "imdb_id": "tt38938066"
  }
]