[
  {
    "name": "The Rookie",
    "type": "series",
    "imdb_id": "tt7587890"
  },
  {
    "name": "The Late Show with Stephen Colbert",
    "type": "series",
    "imdb_id": "tt3697842"
  },
  {
    "name": "FBI",
    "type": "series",
    "imdb_id": "tt7491982"
  },
  {
    "name": "The Daily Show",
    "type": "series",
    "imdb_id": "tt0115147"
  },
  {
    "name": "Star Wars: Maul - Shadow Lord",
    "type": "series",
    "imdb_id": "tt36594331"
  },
  {
    "name": "Watch What Happens Live with Andy Cohen",
    "type": "series",
    "imdb_id": "tt2057880"
  },
  {
    "name": "The Epoch of Miyu",
    "type": "series",
    "imdb_id": "tt35288198"
  },
  {
    "name": "Raw",
    "type": "series",
    "imdb_id": "tt0185103"
  },
  {
    "name": "Binnelanders",
    "type": "series",
    "imdb_id": "tt1527854"
  },
  {
    "name": "Tomorrow Is Ours",
    "type": "series",
    "imdb_id": "tt7124904"
  },
  {
    "name": "Far Away",
    "type": "series",
    "imdb_id": "tt34063491"
  },
  {
    "name": "La promesa",
    "type": "series",
    "imdb_id": "tt22325164"
  },
  {
    "name": "Swallowed Star",
    "type": "series",
    "imdb_id": "tt17050076"
  },
  {
    "name": "Goede Tijden, Slechte Tijden",
    "type": "series",
    "imdb_id": "tt0096597"
  },
  {
    "name": "Dreams of Freedom",
    "type": "series",
    "imdb_id": "tt30002038"
  },
  {
    "name": "Gute Zeiten, schlechte Zeiten",
    "type": "series",
    "imdb_id": "tt0103434"
  },
  {
    "name": "Coronation Street",
    "type": "series",
    "imdb_id": "tt0053494"
  },
  {
    "name": "The Cesaronis",
    "type": "series",
    "imdb_id": "tt0484917"
  },
  {
    "name": "Farming Life in Another World",
    "type": "series",
    "imdb_id": "tt19223420"
  },
  {
    "name": "Witch Hat Atelier",
    "type": "series",
    "imdb_id": "tt32550889"
  }
]