[
  {
    "name": "Tulsa King",
    "type": "series",
    "imdb_id": "tt16358384"
  },
  {
    "name": "Bon Appétit, Your Majesty",
    "type": "series",
    "imdb_id": "tt37600136"
  },
  {
    "name": "The Simpsons",
    "type": "series",
    "imdb_id": "tt0096697"
  },
  {
    "name": "The Walking Dead: Daryl Dixon",
    "type": "series",
    "imdb_id": "tt13062500"
  },
  {
    "name": "The Fragrant Flower Blooms with Dignity",
    "type": "series",
    "imdb_id": "tt36592690"
  },
  {
    "name": "Gachiakuta",
    "type": "series",
    "imdb_id": "tt32612521"
  },
  {
    "name": "Miraculous: Tales of Ladybug & Cat Noir",
    "type": "series",
    "imdb_id": "tt2580046"
  },
  {
    "name": "My Stubborn",
    "type": "series",
    "imdb_id": "tt36601953"
  },
  {
    "name": "Task",
    "type": "series",
    "imdb_id": "tt28013708"
  },
  {
    "name": "Tougen Anki",
    "type": "series",
    "imdb_id": "tt32344704"
  },
  {
    "name": "Scene of the Crime",
    "type": "series",
    "imdb_id": "tt0806910"
  },
  {
    "name": "Running Man",
    "type": "series",
    "imdb_id": "tt2185037"
  },
  {
    "name": "Love's Ambition",
    "type": "series",
    "imdb_id": "tt32582480"
  },
  {
    "name": "Mar afuera",
    "type": "series",
    "imdb_id": "tt32155744"
  },
  {
    "name": "Renegade Immortal",
    "type": "series",
    "imdb_id": "tt27432264"
  },
  {
    "name": "Hello Saturday",
    "type": "series",
    "imdb_id": "tt30985733"
  },
  {
    "name": "Watch What Happens Live with Andy Cohen",
    "type": "series",
    "imdb_id": "tt2057880"
  },
  {
    "name": "Kamen Rider",
    "type": "series",
    "imdb_id": "tt0156214"
  },
  {
    "name": "Confidence Queen",
    "type": "series",
    "imdb_id": "tt37262316"
  }
]