[
  {
    "name": "Hazbin Hotel",
    "type": "series",
    "imdb_id": "tt7216636"
  },
  {
    "name": "The Daily Show",
    "type": "series",
    "imdb_id": "tt0115147"
  },
  {
    "name": "Late Night with Seth Meyers",
    "type": "series",
    "imdb_id": "tt3513388"
  },
  {
    "name": "South Park",
    "type": "series",
    "imdb_id": "tt0121955"
  },
  {
    "name": "Sturm der Liebe",
    "type": "series",
    "imdb_id": "tt0479846"
  },
  {
    "name": "Binnelanders",
    "type": "series",
    "imdb_id": "tt1527854"
  },
  {
    "name": "The Late Show with Stephen Colbert",
    "type": "series",
    "imdb_id": "tt3697842"
  },
  {
    "name": "Campfire Cooking in Another World with My Absurd Skill",
    "type": "series",
    "imdb_id": "tt24229160"
  },
  {
    "name": "Chicago P.D.",
    "type": "series",
    "imdb_id": "tt2805096"
  },
  {
    "name": "Chicago Fire",
    "type": "series",
    "imdb_id": "tt2261391"
  },
  {
    "name": "Strange Tales of Tang Dynasty",
    "type": "series",
    "imdb_id": "tt22797712"
  },
  {
    "name": "Esref Ruya",
    "type": "series",
    "imdb_id": "tt35069642"
  },
  {
    "name": "Dinastía Casillas",
    "type": "series",
    "imdb_id": "tt38629881"
  },
  {
    "name": "The Manipulated",
    "type": "series",
    "imdb_id": "tt36188448"
  },
  {
    "name": "Chicago Med",
    "type": "series",
    "imdb_id": "tt4655480"
  },
  {
    "name": "Suidooster",
    "type": "series",
    "imdb_id": "tt5467444"
  },
  {
    "name": "Markus Lanz",
    "type": "series",
    "imdb_id": "tt1239083"
  },
  {
    "name": "Coronation Street",
    "type": "series",
    "imdb_id": "tt0053494"
  },
  {
    "name": "Survivor",
    "type": "series",
    "imdb_id": "tt0239195"
  },
  {
    "name": "Gute Zeiten, schlechte Zeiten",
    "type": "series",
    "imdb_id": "tt0103434"
  }
]