[
  {
    "name": "Ici tout commence",
    "type": "series",
    "imdb_id": "tt13392064"
  },
  {
    "name": "Jeopardy!",
    "type": "series",
    "imdb_id": "tt0159881"
  },
  {
    "name": "Tomorrow Is Ours",
    "type": "series",
    "imdb_id": "tt7124904"
  },
  {
    "name": "Chronicles of the Sun",
    "type": "series",
    "imdb_id": "tt8883922"
  },
  {
    "name": "Keep Running",
    "type": "series",
    "imdb_id": "tt4325992"
  },
  {
    "name": "Coronation Street",
    "type": "series",
    "imdb_id": "tt0053494"
  },
  {
    "name": "LIVE with Kelly and Mark",
    "type": "series",
    "imdb_id": "tt0096636"
  },
  {
    "name": "Suidooster",
    "type": "series",
    "imdb_id": "tt5467444"
  },
  {
    "name": "Dan Da Dan",
    "type": "series",
    "imdb_id": "tt30217403"
  },
  {
    "name": "Com si fos ahir",
    "type": "series",
    "imdb_id": "tt7331764"
  },
  {
    "name": "Kelders van Geheime",
    "type": "series",
    "imdb_id": "tt32264511"
  },
  {
    "name": "Festa é Festa",
    "type": "series",
    "imdb_id": "tt14156608"
  },
  {
    "name": "Secret Story",
    "type": "series",
    "imdb_id": "tt1364140"
  },
  {
    "name": "Dreams of Liberty",
    "type": "series",
    "imdb_id": "tt30002038"
  },
  {
    "name": "VH1 Top 20 Video Countdown",
    "type": "series",
    "imdb_id": "tt0406482"
  },
  {
    "name": "Hello Saturday",
    "type": "series",
    "imdb_id": "tt30985733"
  },
  {
    "name": "The Bold and the Beautiful",
    "type": "series",
    "imdb_id": "tt0092325"
  },
  {
    "name": "Love Island",
    "type": "series",
    "imdb_id": "tt8819906"
  },
  {
    "name": "Wagle Ki Duniya – Nayi Peedhi Naye Kissey",
    "type": "series",
    "imdb_id": "tt13853152"
  }
]