[
  {
    "name": "The Tudors",
    "type": "series",
    "imdb_id": "tt0758790"
  },
  {
    "name": "You are My Destiny",
    "type": "series",
    "imdb_id": "tt2275419"
  },
  {
    "name": "Maison Ikkoku",
    "type": "series",
    "imdb_id": "tt0090479"
  },
  {
    "name": "Angel Eyes",
    "type": "series",
    "imdb_id": "tt3681890"
  },
  {
    "name": "Sweet Home, Sweet Honey",
    "type": "series",
    "imdb_id": "tt8421804"
  },
  {
    "name": "My Heart Twinkle Twinkle",
    "type": "series",
    "imdb_id": "tt5196080"
  },
  {
    "name": "Rin-ne",
    "type": "series",
    "imdb_id": "tt4584754"
  },
  {
    "name": "Crazy Love",
    "type": "series",
    "imdb_id": "tt3116550"
  },
  {
    "name": "Potato Star 2013QR3",
    "type": "series",
    "imdb_id": "tt3385756"
  },
  {
    "name": "Beautiful You",
    "type": "series",
    "imdb_id": "tt5617936"
  },
  {
    "name": "Head over Heels",
    "type": "series",
    "imdb_id": "tt2983896"
  },
  {
    "name": "The Snow Queen",
    "type": "series",
    "imdb_id": "tt2389644"
  },
  {
    "name": "My Son-In-Law's Woman",
    "type": "series",
    "imdb_id": "tt5546078"
  },
  {
    "name": "Cross Game",
    "type": "series",
    "imdb_id": "tt1414416"
  },
  {
    "name": "Ef: A Tale Of Memories & Melodies",
    "type": "series",
    "imdb_id": "tt1132203"
  },
  {
    "name": "The King's Doctor",
    "type": "series",
    "imdb_id": "tt3364792"
  },
  {
    "name": "Go Princess Go",
    "type": "series",
    "imdb_id": "tt5319572"
  },
  {
    "name": "OniAi",
    "type": "series",
    "imdb_id": "tt2390038"
  },
  {
    "name": "A Thousand Kisses",
    "type": "series",
    "imdb_id": "tt5619630"
  }
]